[{"description": "", "edit": false, "forced": true, "forcedValue": 0, "id": 1736893954436, "name": "%i1", "type": "di", "value": 0}, {"description": "", "edit": false, "forced": true, "forcedValue": 0, "id": 1736893985409, "name": "%m1", "type": "marker", "value": 0}, {"description": "", "edit": false, "forced": false, "forcedValue": 0, "id": 1736894013304, "name": "%o1", "type": "do", "value": 0}, {"description": "", "edit": false, "forced": false, "forcedValue": 0, "id": 1740783815807, "name": "%m6", "type": "marker", "value": 1}, {"description": "", "edit": false, "forced": false, "forcedValue": 0, "id": 1740785108626, "name": "%i2", "type": "di", "value": 0}, {"id": 1740867169637, "name": "%m3", "type": "marker", "description": "", "edit": false, "value": 0, "forced": false, "forcedValue": 0}]